epicprint/Print.py
epicprint/__init__.py
epicprint/test.py
epicprint-0.4.dist-info/METADATA
epicprint-0.4.dist-info/RECORD
epicprint-0.4.dist-info/WHEEL
epicprint-0.4.dist-info/top_level.txt
