Metadata-Version: 2.1
Name: epicprint
Version: 0.4
Summary: Custom print with superpowers
Home-page: https://github.com/ajthinking/epicprint
Author: Anders Jürisoo
Author-email: jurisoo@hotmail.com
License: UNKNOWN
Platform: UNKNOWN
Classifier: Programming Language :: Python :: 3
Classifier: License :: OSI Approved :: MIT License
Classifier: Operating System :: OS Independent
